niwrap_workbench/workbench/__init__.py
niwrap_workbench/workbench/annotation_resample.py
niwrap_workbench/workbench/backend_average_dense_roi.py
niwrap_workbench/workbench/backend_average_roi_correlation.py
niwrap_workbench/workbench/border_export_color_table.py
niwrap_workbench/workbench/border_file_export_to_caret5.py
niwrap_workbench/workbench/border_length.py
niwrap_workbench/workbench/border_merge.py
niwrap_workbench/workbench/border_resample.py
niwrap_workbench/workbench/border_to_rois.py
niwrap_workbench/workbench/border_to_vertices.py
niwrap_workbench/workbench/cifti_all_labels_to_rois.py
niwrap_workbench/workbench/cifti_average.py
niwrap_workbench/workbench/cifti_average_dense_roi.py
niwrap_workbench/workbench/cifti_average_roi_correlation.py
niwrap_workbench/workbench/cifti_change_mapping.py
niwrap_workbench/workbench/cifti_convert.py
niwrap_workbench/workbench/cifti_correlation.py
niwrap_workbench/workbench/cifti_correlation_gradient.py
niwrap_workbench/workbench/cifti_create_dense_from_template.py
niwrap_workbench/workbench/cifti_create_dense_scalar.py
niwrap_workbench/workbench/cifti_create_dense_timeseries.py
niwrap_workbench/workbench/cifti_create_label.py
niwrap_workbench/workbench/cifti_create_parcellated_from_template.py
niwrap_workbench/workbench/cifti_create_scalar_series.py
niwrap_workbench/workbench/cifti_cross_correlation.py
niwrap_workbench/workbench/cifti_dilate.py
niwrap_workbench/workbench/cifti_erode.py
niwrap_workbench/workbench/cifti_estimate_fwhm.py
niwrap_workbench/workbench/cifti_export_dense_mapping.py
niwrap_workbench/workbench/cifti_extrema.py
niwrap_workbench/workbench/cifti_false_correlation.py
niwrap_workbench/workbench/cifti_find_clusters.py
niwrap_workbench/workbench/cifti_gradient.py
niwrap_workbench/workbench/cifti_label_adjacency.py
niwrap_workbench/workbench/cifti_label_export_table.py
niwrap_workbench/workbench/cifti_label_import.py
niwrap_workbench/workbench/cifti_label_modify_keys.py
niwrap_workbench-0.8.3.dist-info/WHEEL
niwrap_workbench-0.8.3.dist-info/METADATA
niwrap_workbench-0.8.3.dist-info/RECORD
